turtle_utils/__init__.py
turtle_utils/auto_generate_api_case_allpairspy.py
turtle_utils/curl_generate_util.py
turtle_utils/data_util.py
turtle_utils/exception_util.py
turtle_utils/mongo_connect.py
turtle_utils/mongo_public.py
turtle_utils/mysql_connect.py
turtle_utils/mysql_public.py
turtle_utils/operation_datas.py
turtle_utils/operation_logging.py
turtle_utils/operation_request_data.py
turtle_utils/operation_yaml.py
turtle_utils/oss.py
turtle_utils/other_util.py
turtle_utils/redis_connect.py
turtle_utils/redis_public.py
turtle_utils/request_main.py
turtle_utils/send_email.py
turtle_utils/servers_util.py
turtle_utils/swagger_api_parse.py
turtle_utils/time_util.py
turtle_utils/update_api_case_allpairspy_case.py
turtle_utils/update_metaverse_config.py
turtle_utils/wrapper_util.py
turtle_utils-1.0.1.dist-info/METADATA
turtle_utils-1.0.1.dist-info/WHEEL
turtle_utils-1.0.1.dist-info/top_level.txt
turtle_utils-1.0.1.dist-info/RECORD
