Metadata-Version: 2.1
Name: turtle-utils
Version: 1.0.1
Summary: 个人项目常用工具类
Home-page: UNKNOWN
Author: qtclm
Author-email: 248313385@qq.com
License: MIT
Platform: UNKNOWN
Classifier: Development Status :: 1 - Planning
Classifier: Intended Audience :: Developers
Classifier: Programming Language :: Python :: 3
Classifier: Operating System :: Unix
Classifier: Operating System :: MacOS :: MacOS X
Classifier: Operating System :: Microsoft :: Windows
